Metadata-Version: 2.1
Name: numpydoc-lint
Version: 1.0.0
Summary: Run numpydoc.validate on all docstrings in a package.
Home-page: UNKNOWN
Author: Bruno Beltran <brunobeltran0@gmail.com>
License: UNKNOWN
Platform: UNKNOWN
Requires-Python: >=3.7
